{"content":[{"id":"481a9449","settings":{"background_background":"classic","background_image":{"id":"","url":""},"background_position":"center center","background_position_mobile":"center center","background_repeat":"no-repeat","background_repeat_mobile":"no-repeat","background_size":"cover","background_size_mobile":"cover","background_bg_width_tablet":{"unit":"%","size":130,"sizes":[]},"background_bg_width_mobile":{"unit":"%","size":"","sizes":[]},"background_overlay_background":"classic","background_overlay_position":"top left","padding_tablet":{"unit":"px","top":"40","right":"0","bottom":"0","left":"0","isLinked":false},"background_overlay_opacity":{"unit":"px","size":1,"sizes":[]},"_title":"footer","shape_divider_top_color":"#FFFFFF","shape_divider_top_width":{"unit":"%","size":100,"sizes":[]},"shape_divider_top_height":{"unit":"px","size":25,"sizes":[]},"flex_direction":"column","flex_align_items":"stretch","flex_gap":{"size":10,"unit":"px"},"background_color":"#121212"},"elements":[{"id":"736e3506","settings":{"flex_direction":"row","margin":{"unit":"px","top":"-85","right":"0","bottom":"0","left":"0","isLinked":false},"_title":"contact info","margin_mobile":{"unit":"px","top":"0","right":"0","bottom":"0","left":"0","isLinked":true}},"elements":[{"id":"2a4fed73","settings":{"boxed_width":{"unit":"%","size":"","sizes":[]},"boxed_width_tablet":{"unit":"%","size":"","sizes":[]},"boxed_width_mobile":{"unit":"%","size":"","sizes":[]},"flex_justify_content":"center","width_tablet":{"unit":"%","size":30,"sizes":[]},"width_mobile":{"unit":"%","size":"","sizes":[]},"background_background":"classic","_title":"Container"},"elements":[{"id":"3fd952c0","settings":{"card_icon":{"value":"far fa-envelope","library":"fa-regular"},"card_title":"Mail Us","card_description":"info@yoursite.com","card_bg_color_color":"#121212","card_border_type_border":"solid","card_border_radius":{"unit":"px","top":"100","right":"100","bottom":"100","left":"100","isLinked":true},"card_padding":{"unit":"px","top":"25","right":"25","bottom":"25","left":"25","isLinked":true},"card_box_shadow_box_shadow_type":"yes","card_box_shadow_box_shadow":{"horizontal":0,"vertical":0,"blur":0,"spread":0,"color":"rgba(0,0,0,0.5)"},"card_heading_icon_alignment":"center","card_heading_icon_bg_color_color":"#EB0029","card_heading_icon_color":"#FFFFFF","icon_width":{"unit":"px","size":50,"sizes":[]},"icon_size":{"unit":"px","size":25,"sizes":[]},"icon_border_type":{"unit":"%","top":"50","right":"50","bottom":"50","left":"50","isLinked":true},"icon_box_shadow_box_shadow":{"horizontal":0,"vertical":2,"blur":4,"spread":0,"color":"rgba(97, 97, 97, 0.58)"},"card_heading_title_alignment":"left","card_heading_title_color":"#FFFFFF","card_heading_title_typography_typography":"custom","card_heading_title_typography_font_family":"Arima","card_heading_title_typography_font_size":{"unit":"rem","size":1.399999999999999911182158029987476766109466552734375,"sizes":[]},"card_heading_title_typography_font_size_tablet":{"unit":"rem","size":1.100000000000000088817841970012523233890533447265625,"sizes":[]},"card_heading_title_typography_font_size_mobile":{"unit":"rem","size":"","sizes":[]},"card_heading_title_typography_font_weight":"700","card_heading_title_typography_letter_spacing":{"unit":"px","size":-0.200000000000000011102230246251565404236316680908203125,"sizes":[]},"card_heading_description_alignment":"left","card_heading_description_color":"#E1E1E1","card_heading_description_typography_typography":"custom","card_heading_description_typography_font_family":"Jost","card_heading_description_typography_font_size":{"unit":"rem","size":1.100000000000000088817841970012523233890533447265625,"sizes":[]},"card_heading_description_typography_font_size_tablet":{"unit":"rem","size":1,"sizes":[]},"card_heading_description_typography_font_size_mobile":{"unit":"rem","size":"","sizes":[]},"card_heading_description_typography_font_weight":"400","card_bg_image":{"id":1952,"url":"https:\/\/wpennova.com\/restaurant\/wp-content\/uploads\/2023\/08\/placeholder-2-1.png"},"card_image":{"id":1953,"url":"https:\/\/wpennova.com\/restaurant\/wp-content\/uploads\/2023\/08\/placeholder-3-1.png"},"card_border_type_width":{"unit":"px","top":"1","right":"1","bottom":"1","left":"1","isLinked":true},"card_border_type_color":"#343B36","feature_icon_position":"row","card_heading_icon_margin":{"unit":"px","top":"0","right":"15","bottom":"0","left":"0","isLinked":false},"card_padding_tablet":{"unit":"px","top":"15","right":"15","bottom":"15","left":"15","isLinked":true},"icon_width_tablet":{"unit":"px","size":40,"sizes":[]},"icon_size_tablet":{"unit":"px","size":16,"sizes":[]}},"elements":[],"isInner":false,"widgetType":"ennova-feature","elType":"widget"}],"isInner":true,"elType":"container"},{"id":"65bd1edd","settings":{"boxed_width":{"unit":"%","size":"","sizes":[]},"boxed_width_tablet":{"unit":"%","size":"","sizes":[]},"boxed_width_mobile":{"unit":"%","size":"","sizes":[]},"flex_justify_content":"center","width_tablet":{"unit":"%","size":50,"sizes":[]},"width_mobile":{"unit":"%","size":"","sizes":[]},"background_background":"classic"},"elements":[{"id":"70a8a628","settings":{"card_icon":{"value":"fas fa-phone-volume","library":"fa-solid"},"card_title":"Contact Us","card_description":"(+1) 1234 56 789","card_bg_color_color":"#121212","card_border_type_border":"solid","card_border_radius":{"unit":"px","top":"100","right":"100","bottom":"100","left":"100","isLinked":true},"card_padding":{"unit":"px","top":"25","right":"25","bottom":"25","left":"25","isLinked":true},"card_box_shadow_box_shadow_type":"yes","card_box_shadow_box_shadow":{"horizontal":0,"vertical":0,"blur":0,"spread":0,"color":"rgba(0,0,0,0.5)"},"card_heading_icon_alignment":"center","card_heading_icon_bg_color_color":"#EB0029","card_heading_icon_color":"#FFFFFF","icon_width":{"unit":"px","size":50,"sizes":[]},"icon_size":{"unit":"px","size":25,"sizes":[]},"icon_border_type":{"unit":"%","top":"50","right":"50","bottom":"50","left":"50","isLinked":true},"icon_box_shadow_box_shadow":{"horizontal":0,"vertical":2,"blur":4,"spread":0,"color":"rgba(97, 97, 97, 0.58)"},"card_heading_title_alignment":"left","card_heading_title_color":"#FFFFFF","card_heading_title_typography_typography":"custom","card_heading_title_typography_font_family":"Arima","card_heading_title_typography_font_size":{"unit":"rem","size":1.399999999999999911182158029987476766109466552734375,"sizes":[]},"card_heading_title_typography_font_size_tablet":{"unit":"rem","size":1.100000000000000088817841970012523233890533447265625,"sizes":[]},"card_heading_title_typography_font_size_mobile":{"unit":"rem","size":"","sizes":[]},"card_heading_title_typography_font_weight":"700","card_heading_title_typography_letter_spacing":{"unit":"px","size":-0.200000000000000011102230246251565404236316680908203125,"sizes":[]},"card_heading_description_alignment":"left","card_heading_description_color":"#E1E1E1","card_heading_description_typography_typography":"custom","card_heading_description_typography_font_family":"Jost","card_heading_description_typography_font_size":{"unit":"rem","size":1.100000000000000088817841970012523233890533447265625,"sizes":[]},"card_heading_description_typography_font_size_tablet":{"unit":"rem","size":1,"sizes":[]},"card_heading_description_typography_font_size_mobile":{"unit":"rem","size":"","sizes":[]},"card_heading_description_typography_font_weight":"400","card_bg_image":{"id":1952,"url":"https:\/\/wpennova.com\/restaurant\/wp-content\/uploads\/2023\/08\/placeholder-2-1.png"},"card_image":{"id":1953,"url":"https:\/\/wpennova.com\/restaurant\/wp-content\/uploads\/2023\/08\/placeholder-3-1.png"},"card_border_type_width":{"unit":"px","top":"1","right":"1","bottom":"1","left":"1","isLinked":true},"card_border_type_color":"#343B36","feature_icon_position":"row","card_heading_icon_margin":{"unit":"px","top":"0","right":"15","bottom":"0","left":"0","isLinked":false},"card_padding_tablet":{"unit":"px","top":"15","right":"15","bottom":"15","left":"15","isLinked":true},"icon_width_tablet":{"unit":"px","size":40,"sizes":[]},"icon_size_tablet":{"unit":"px","size":16,"sizes":[]}},"elements":[],"isInner":false,"widgetType":"ennova-feature","elType":"widget"}],"isInner":true,"elType":"container"},{"id":"55a1fcb9","settings":{"boxed_width":{"unit":"%","size":"","sizes":[]},"boxed_width_tablet":{"unit":"%","size":"","sizes":[]},"boxed_width_mobile":{"unit":"%","size":"","sizes":[]},"flex_justify_content":"center","width_tablet":{"unit":"%","size":50,"sizes":[]},"width_mobile":{"unit":"%","size":"","sizes":[]},"background_background":"classic","hide_tablet":"hidden-tablet"},"elements":[{"id":"262f389","settings":{"card_icon":{"value":"fas fa-map-marker-alt","library":"fa-solid"},"card_title":"Address","card_description":"1240 Park Ave, New York","card_bg_color_color":"#121212","card_border_type_border":"solid","card_border_radius":{"unit":"px","top":"100","right":"100","bottom":"100","left":"100","isLinked":true},"card_padding":{"unit":"px","top":"25","right":"25","bottom":"25","left":"25","isLinked":true},"card_box_shadow_box_shadow_type":"yes","card_box_shadow_box_shadow":{"horizontal":0,"vertical":0,"blur":0,"spread":0,"color":"rgba(0,0,0,0.5)"},"card_heading_icon_alignment":"center","card_heading_icon_bg_color_color":"#EB0029","card_heading_icon_color":"#FFFFFF","icon_width":{"unit":"px","size":50,"sizes":[]},"icon_size":{"unit":"px","size":25,"sizes":[]},"icon_border_type":{"unit":"%","top":"50","right":"50","bottom":"50","left":"50","isLinked":true},"icon_box_shadow_box_shadow":{"horizontal":0,"vertical":2,"blur":4,"spread":0,"color":"rgba(97, 97, 97, 0.58)"},"card_heading_title_alignment":"left","card_heading_title_color":"#FFFFFF","card_heading_title_typography_typography":"custom","card_heading_title_typography_font_family":"Arima","card_heading_title_typography_font_size":{"unit":"rem","size":1.399999999999999911182158029987476766109466552734375,"sizes":[]},"card_heading_title_typography_font_size_tablet":{"unit":"rem","size":1.100000000000000088817841970012523233890533447265625,"sizes":[]},"card_heading_title_typography_font_size_mobile":{"unit":"rem","size":"","sizes":[]},"card_heading_title_typography_font_weight":"700","card_heading_title_typography_letter_spacing":{"unit":"px","size":-0.200000000000000011102230246251565404236316680908203125,"sizes":[]},"card_heading_description_alignment":"left","card_heading_description_color":"#E1E1E1","card_heading_description_typography_typography":"custom","card_heading_description_typography_font_family":"Jost","card_heading_description_typography_font_size":{"unit":"rem","size":1.100000000000000088817841970012523233890533447265625,"sizes":[]},"card_heading_description_typography_font_size_tablet":{"unit":"rem","size":1,"sizes":[]},"card_heading_description_typography_font_size_mobile":{"unit":"rem","size":"","sizes":[]},"card_heading_description_typography_font_weight":"400","card_bg_image":{"id":1952,"url":"https:\/\/wpennova.com\/restaurant\/wp-content\/uploads\/2023\/08\/placeholder-2-1.png"},"card_image":{"id":1953,"url":"https:\/\/wpennova.com\/restaurant\/wp-content\/uploads\/2023\/08\/placeholder-3-1.png"},"card_border_type_width":{"unit":"px","top":"1","right":"1","bottom":"1","left":"1","isLinked":true},"card_border_type_color":"#343B36","feature_icon_position":"row","card_heading_icon_margin":{"unit":"px","top":"0","right":"15","bottom":"0","left":"0","isLinked":false},"card_padding_tablet":{"unit":"px","top":"15","right":"15","bottom":"15","left":"15","isLinked":true},"icon_width_tablet":{"unit":"px","size":40,"sizes":[]},"icon_size_tablet":{"unit":"px","size":16,"sizes":[]}},"elements":[],"isInner":false,"widgetType":"ennova-feature","elType":"widget"}],"isInner":true,"elType":"container"}],"isInner":true,"elType":"container"},{"id":"47265aef","settings":{"structure":"40","flex_direction":"row","flex_align_items":"stretch","flex_gap":{"size":10,"unit":"px"},"content_width":"full","container_type":"grid","min_height":{"unit":"px","size":0,"sizes":[]},"grid_outline":"","grid_columns_grid":{"unit":"fr","size":4,"sizes":[]},"grid_rows_grid":{"unit":"fr","size":0,"sizes":[]},"grid_gaps":{"unit":"px","top":"","right":"","bottom":"","left":"","isLinked":true,"column":"0","row":"0"},"grid_columns_grid_tablet":{"unit":"fr","size":2,"sizes":[]},"grid_rows_grid_tablet":{"unit":"fr","size":0,"sizes":[]},"margin":{"unit":"px","top":"30","right":"0","bottom":"20","left":"0","isLinked":false},"_title":"footer-text"},"elements":[{"id":"6cc5e4ca","settings":{"_column_size":25,"width":{"unit":"%","size":""},"width_tablet":{"size":"","unit":"%"},"content_width":"full","_flex_size":"none","_element_width":"initial"},"elements":[{"id":"65c099a","settings":{"align":"left","image_width":{"unit":"px","size":200,"sizes":[]},"image_width_tablet":{"unit":"px","size":170,"sizes":[]},"use":"custom","image":{"id":1476,"url":"https:\/\/wpennova.com\/restaurant\/wp-content\/uploads\/2023\/08\/dfg.png","alt":"","source":"library","size":""},"align_tablet":"left","align_mobile":"center"},"elements":[],"isInner":false,"widgetType":"ennova-site-logo","elType":"widget"},{"id":"11e7db87","settings":{"title":"They have downloaded gmail and seems to be working","align":"left","title_color":"#BDBDBD","typography_typography":"custom","typography_font_family":"Jost","typography_font_size":{"unit":"rem","size":1.100000000000000088817841970012523233890533447265625,"sizes":[]},"typography_font_size_tablet":{"unit":"rem","size":1,"sizes":[]},"typography_font_size_mobile":{"unit":"px","size":16,"sizes":[]},"typography_font_weight":"400","typography_line_height":{"unit":"em","size":1.600000000000000088817841970012523233890533447265625,"sizes":[]},"typography_letter_spacing":{"unit":"px","size":0.1000000000000000055511151231257827021181583404541015625,"sizes":[]},"header_size":"p","_margin":{"unit":"px","top":"15","right":"0","bottom":"0","left":"0","isLinked":false},"_margin_tablet":{"unit":"px","top":"0","right":"0","bottom":"0","left":"0","isLinked":false},"align_mobile":"center"},"elements":[],"isInner":false,"widgetType":"heading","elType":"widget"},{"id":"3ebd126a","settings":{"social_icon_list":[{"social_icon":{"value":"fab fa-facebook-f","library":"fa-brands"},"_id":"7738ad5"},{"social_icon":{"value":"fab fa-twitter","library":"fa-brands"},"_id":"a72373b"},{"social_icon":{"value":"fab fa-instagram","library":"fa-brands"},"_id":"50bce90"},{"social_icon":{"value":"fab fa-linkedin-in","library":"fa-brands"},"_id":"6d18995"}],"align":"left","icon_color":"custom","icon_primary_color":"#2C2C2C","icon_secondary_color":"#FFFFFF","icon_size":{"unit":"px","size":13,"sizes":[]},"icon_padding":{"unit":"em","size":1,"sizes":[]},"image_border_width":{"unit":"px","top":"2","right":"2","bottom":"2","left":"2","isLinked":true},"image_border_color":"#1F3854","border_radius":{"unit":"px","top":"25","right":"25","bottom":"25","left":"25","isLinked":true},"hover_primary_color":"#EB0029","hover_secondary_color":"#FFFFFF","hover_border_color":"#5097EF","icon_size_tablet":{"unit":"px","size":13,"sizes":[]},"icon_padding_tablet":{"unit":"em","size":0.8000000000000000444089209850062616169452667236328125,"sizes":[]},"icon_spacing_tablet":{"unit":"px","size":5,"sizes":[]},"align_mobile":"center","icon_spacing":{"unit":"px","size":8,"sizes":[]}},"elements":[],"isInner":false,"widgetType":"social-icons","elType":"widget"}],"isInner":true,"elType":"container"},{"id":"647d70c5","settings":{"_column_size":25,"width":{"size":null,"unit":"%"},"width_tablet":{"size":"","unit":"%"},"content_width":"full","margin":{"unit":"px","top":"20","right":"0","bottom":"0","left":"0","isLinked":false}},"elements":[{"id":"733f933e","settings":{"title":"Our Menu","align":"left","title_color":"#FFFFFF","typography_typography":"custom","typography_font_family":"Arima","typography_font_size":{"unit":"rem","size":1.399999999999999911182158029987476766109466552734375,"sizes":[]},"typography_font_size_tablet":{"unit":"rem","size":1.1999999999999999555910790149937383830547332763671875,"sizes":[]},"typography_font_size_mobile":{"unit":"rem","size":"","sizes":[]},"typography_font_weight":"500","typography_line_height":{"unit":"rem","size":"","sizes":[]},"typography_line_height_tablet":{"unit":"rem","size":"","sizes":[]},"typography_line_height_mobile":{"unit":"rem","size":"","sizes":[]},"typography_letter_spacing":{"unit":"px","size":0.1000000000000000055511151231257827021181583404541015625,"sizes":[]},"align_mobile":"left","_padding":{"unit":"px","top":"4","right":"0","bottom":"0","left":"8","isLinked":false},"_flex_align_self":"flex-start","_flex_order":"start","_background_background":"classic","_background_color_stop":{"unit":"%","size":40,"sizes":[]},"_background_color_b":"#A2001C","_background_gradient_angle":{"unit":"deg","size":140,"sizes":[]},"_border_border":"solid","_border_width":{"unit":"px","top":"0","right":"0","bottom":"0","left":"2","isLinked":false},"_border_color":"#EB0029","_border_radius":{"unit":"px","top":"4","right":"4","bottom":"4","left":"4","isLinked":true},"_flex_align_self_mobile":"center"},"elements":[],"isInner":false,"widgetType":"heading","elType":"widget"},{"id":"73bc39e6","settings":{"icon_list":[{"text":"Vegetarian Fried","selected_icon":{"value":"fas fa-arrow-right","library":"fa-solid"},"link":{"url":"#","is_external":"","nofollow":"","custom_attributes":""},"_id":"fbdc84c"},{"text":"Pasta With Fish","selected_icon":{"value":"fas fa-arrow-right","library":"fa-solid"},"link":{"url":"#","is_external":"","nofollow":"","custom_attributes":""},"_id":"281d972"},{"text":"Fillet with Salad","selected_icon":{"value":"fas fa-arrow-right","library":"fa-solid"},"link":{"url":"#","is_external":"","nofollow":"","custom_attributes":""},"_id":"d5546a1"},{"text":"Tuscan Flatbread","selected_icon":{"value":"fas fa-arrow-right","library":"fa-solid"},"link":{"url":"#","is_external":"","nofollow":"","custom_attributes":""},"_id":"0993ec5"},{"text":"Almond Baked Brie","selected_icon":{"value":"fas fa-arrow-right","library":"fa-solid"},"link":{"url":"#","is_external":"","nofollow":"","custom_attributes":""},"_id":"e280343"},{"text":"Vegetarian Soup","selected_icon":{"value":"fas fa-arrow-right","library":"fa-solid"},"link":{"url":"#","is_external":"","nofollow":"","custom_attributes":""},"_id":"6e875e0"}],"space_between":{"unit":"px","size":22,"sizes":[]},"icon_align":"left","icon_color":"#BDBDBD","icon_color_hover":"#EB0029","icon_size":{"unit":"rem","size":0.59999999999999997779553950749686919152736663818359375,"sizes":[]},"icon_size_tablet":{"unit":"rem","size":"","sizes":[]},"icon_size_mobile":{"unit":"rem","size":"","sizes":[]},"text_indent":{"unit":"px","size":0,"sizes":[]},"icon_self_align":"center","icon_self_vertical_align":"center","icon_typography_typography":"custom","icon_typography_font_family":"Jost","icon_typography_font_size":{"unit":"rem","size":1.100000000000000088817841970012523233890533447265625,"sizes":[]},"icon_typography_font_size_tablet":{"unit":"rem","size":1,"sizes":[]},"icon_typography_font_size_mobile":{"unit":"rem","size":"","sizes":[]},"icon_typography_font_weight":"400","text_color":"#BDBDBD","text_color_hover":"#EB0029","_margin":{"unit":"px","top":"20","right":"0","bottom":"0","left":"0","isLinked":false},"icon_typography_line_height":{"unit":"rem","size":"","sizes":[]},"icon_typography_line_height_tablet":{"unit":"rem","size":"","sizes":[]},"icon_typography_line_height_mobile":{"unit":"rem","size":"","sizes":[]},"_margin_tablet":{"unit":"px","top":"0","right":"0","bottom":"0","left":"0","isLinked":false},"_margin_mobile":{"unit":"px","top":"0","right":"0","bottom":"0","left":"0","isLinked":false},"space_between_tablet":{"unit":"px","size":18,"sizes":[]},"icon_align_mobile":"center","space_between_mobile":{"unit":"px","size":15,"sizes":[]}},"elements":[],"isInner":false,"widgetType":"icon-list","elType":"widget"}],"isInner":true,"elType":"container"},{"id":"21aa464b","settings":{"_column_size":25,"width":{"size":null,"unit":"%"},"width_tablet":{"size":"","unit":"%"},"content_width":"full","_element_width":"initial","margin":{"unit":"px","top":"20","right":"0","bottom":"0","left":"0","isLinked":false}},"elements":[{"id":"1364f098","settings":{"title":"Our Links","align":"left","title_color":"#FFFFFF","typography_typography":"custom","typography_font_family":"Arima","typography_font_size":{"unit":"rem","size":1.399999999999999911182158029987476766109466552734375,"sizes":[]},"typography_font_size_tablet":{"unit":"rem","size":1.1999999999999999555910790149937383830547332763671875,"sizes":[]},"typography_font_size_mobile":{"unit":"rem","size":"","sizes":[]},"typography_font_weight":"500","typography_line_height":{"unit":"rem","size":"","sizes":[]},"typography_line_height_tablet":{"unit":"rem","size":"","sizes":[]},"typography_line_height_mobile":{"unit":"rem","size":"","sizes":[]},"typography_letter_spacing":{"unit":"px","size":0.1000000000000000055511151231257827021181583404541015625,"sizes":[]},"_margin":{"unit":"px","top":"0","right":"0","bottom":"0","left":"0","isLinked":false},"align_mobile":"center","_padding":{"unit":"px","top":"4","right":"0","bottom":"0","left":"8","isLinked":false},"_flex_align_self":"flex-start","_flex_order":"start","_background_background":"classic","_background_color_stop":{"unit":"%","size":40,"sizes":[]},"_background_color_b":"#A2001C","_background_gradient_angle":{"unit":"deg","size":140,"sizes":[]},"_border_border":"solid","_border_width":{"unit":"px","top":"0","right":"0","bottom":"0","left":"2","isLinked":false},"_border_color":"#EB0029","_border_radius":{"unit":"px","top":"4","right":"4","bottom":"4","left":"4","isLinked":true},"_flex_align_self_mobile":"center"},"elements":[],"isInner":false,"widgetType":"heading","elType":"widget"},{"id":"4d37b24e","settings":{"icon_list":[{"text":"Order Tracking","selected_icon":{"value":"fas fa-arrow-right","library":"fa-solid"},"_id":"fc52df6","link":{"url":"#","is_external":"","nofollow":"","custom_attributes":""}},{"text":"Warranty and Services","selected_icon":{"value":"fas fa-arrow-right","library":"fa-solid"},"link":{"url":"#","is_external":"","nofollow":"","custom_attributes":""},"_id":"fbdc84c"},{"text":"About","selected_icon":{"value":"fas fa-arrow-right","library":"fa-solid"},"link":{"url":"#","is_external":"","nofollow":"","custom_attributes":""},"_id":"281d972"},{"text":"Contact Us","selected_icon":{"value":"fas fa-arrow-right","library":"fa-solid"},"link":{"url":"#","is_external":"","nofollow":"","custom_attributes":""},"_id":"0993ec5"},{"text":"Wishlist","selected_icon":{"value":"fas fa-arrow-right","library":"fa-solid"},"link":{"url":"#","is_external":"","nofollow":"","custom_attributes":""},"_id":"d5546a1"}],"space_between":{"unit":"px","size":22,"sizes":[]},"icon_align":"left","icon_color":"#BDBDBD","icon_color_hover":"#EB0029","icon_size":{"unit":"rem","size":0.59999999999999997779553950749686919152736663818359375,"sizes":[]},"icon_size_tablet":{"unit":"rem","size":"","sizes":[]},"icon_size_mobile":{"unit":"rem","size":"","sizes":[]},"text_indent":{"unit":"px","size":0,"sizes":[]},"icon_self_align":"center","icon_self_vertical_align":"center","icon_typography_typography":"custom","icon_typography_font_family":"Jost","icon_typography_font_size":{"unit":"rem","size":1.100000000000000088817841970012523233890533447265625,"sizes":[]},"icon_typography_font_size_tablet":{"unit":"rem","size":1,"sizes":[]},"icon_typography_font_size_mobile":{"unit":"rem","size":"","sizes":[]},"icon_typography_font_weight":"400","text_color":"#BDBDBD","text_color_hover":"#EB0029","_margin":{"unit":"px","top":"20","right":"0","bottom":"0","left":"0","isLinked":false},"icon_typography_line_height":{"unit":"rem","size":"","sizes":[]},"icon_typography_line_height_tablet":{"unit":"rem","size":"","sizes":[]},"icon_typography_line_height_mobile":{"unit":"rem","size":"","sizes":[]},"_margin_tablet":{"unit":"px","top":"0","right":"0","bottom":"0","left":"0","isLinked":false},"_margin_mobile":{"unit":"px","top":"0","right":"0","bottom":"0","left":"0","isLinked":false},"space_between_tablet":{"unit":"px","size":18,"sizes":[]},"icon_align_mobile":"center","space_between_mobile":{"unit":"px","size":15,"sizes":[]}},"elements":[],"isInner":false,"widgetType":"icon-list","elType":"widget"}],"isInner":true,"elType":"container"},{"id":"57c3a162","settings":{"_column_size":25,"width":{"size":null,"unit":"%"},"width_tablet":{"size":"","unit":"%"},"content_width":"full","margin":{"unit":"px","top":"20","right":"0","bottom":"0","left":"0","isLinked":false}},"elements":[{"id":"2e965e2d","settings":{"title":"Opening Hours","align":"left","title_color":"#FFFFFF","typography_typography":"custom","typography_font_family":"Arima","typography_font_size":{"unit":"rem","size":1.399999999999999911182158029987476766109466552734375,"sizes":[]},"typography_font_size_tablet":{"unit":"rem","size":1.1999999999999999555910790149937383830547332763671875,"sizes":[]},"typography_font_size_mobile":{"unit":"rem","size":"","sizes":[]},"typography_font_weight":"500","typography_line_height":{"unit":"rem","size":"","sizes":[]},"typography_line_height_tablet":{"unit":"rem","size":"","sizes":[]},"typography_line_height_mobile":{"unit":"rem","size":"","sizes":[]},"typography_letter_spacing":{"unit":"px","size":0.1000000000000000055511151231257827021181583404541015625,"sizes":[]},"_margin":{"unit":"px","top":"0","right":"0","bottom":"0","left":"0","isLinked":false},"align_mobile":"center","_padding":{"unit":"px","top":"4","right":"0","bottom":"0","left":"8","isLinked":false},"_flex_align_self":"flex-start","_flex_order":"start","_background_background":"classic","_background_color_stop":{"unit":"%","size":40,"sizes":[]},"_background_color_b":"#A2001C","_background_gradient_angle":{"unit":"deg","size":140,"sizes":[]},"_border_border":"solid","_border_width":{"unit":"px","top":"0","right":"0","bottom":"0","left":"2","isLinked":false},"_border_color":"#EB0029","_border_radius":{"unit":"px","top":"4","right":"4","bottom":"4","left":"4","isLinked":true},"_flex_align_self_mobile":"center"},"elements":[],"isInner":false,"widgetType":"heading","elType":"widget"},{"id":"48d865b0","settings":{"card_title":"","header_description":"","footer_description":"","business_hours_block":[{"business_hours_title":"Mon-Fri","business_hours_text":"10 AM \u2013 9 PM","_id":"510b2ec"},{"business_hours_title":"Saturday","business_hours_text":"09 AM \u2013 5 PM","_id":"2823030"},{"business_hours_title":"Sunday: ","_id":"e7e6ed3","business_hours_text":"Open"}],"show_header_title":"","show_header_text":"","show_footer_text":"","feature_list_title_color":"#BDBDBD","feature_list_title_typography_typography":"custom","feature_list_title_typography_font_family":"Jost","feature_list_title_typography_font_size":{"unit":"rem","size":1,"sizes":[]},"feature_list_title_typography_font_size_tablet":{"unit":"rem","size":0.90000000000000002220446049250313080847263336181640625,"sizes":[]},"feature_list_title_typography_font_size_mobile":{"unit":"rem","size":1,"sizes":[]},"feature_list_title_typography_font_weight":"400","feature_list_text_color":"#EB0029","feature_list_text_typography_typography":"custom","feature_list_text_typography_font_family":"Jost","feature_list_text_typography_font_size":{"unit":"rem","size":0.90000000000000002220446049250313080847263336181640625,"sizes":[]},"feature_list_text_typography_font_size_tablet":{"unit":"rem","size":0.90000000000000002220446049250313080847263336181640625,"sizes":[]},"feature_list_text_typography_font_size_mobile":{"unit":"rem","size":"","sizes":[]},"feature_list_text_typography_font_weight":"600","feature_list_padding":{"unit":"px","top":"0","right":"0","bottom":"0","left":"0","isLinked":false},"_margin":{"unit":"px","top":"20","right":"0","bottom":"0","left":"0","isLinked":false},"feature_list_padding_tablet":{"unit":"px","top":"0","right":"0","bottom":"0","left":"0","isLinked":false},"card_border_radius":{"unit":"px","top":"0","right":"0","bottom":"0","left":"0","isLinked":false},"feature_separator_margin_tablet":{"unit":"px","top":"15","right":"15","bottom":"15","left":"15","isLinked":true},"_margin_mobile":{"unit":"px","top":"0","right":"0","bottom":"0","left":"0","isLinked":false},"ennova_control_get_pro":"1","card_bg_color":"#FFFFFF00","card_border_type_width":{"unit":"px","top":"1","right":"1","bottom":"5","left":"1","isLinked":false},"card_border_type_color":"#464858","card_feature_padding":{"unit":"px","top":"0","right":"50","bottom":"0","left":"0","isLinked":false},"feature_separator_margin":{"unit":"px","top":"20","right":"0","bottom":"0","left":"0","isLinked":false},"card_feature_padding_mobile":{"unit":"px","top":"0","right":"0","bottom":"0","left":"0","isLinked":false},"_margin_tablet":{"unit":"px","top":"10","right":"0","bottom":"0","left":"0","isLinked":false}},"elements":[],"isInner":false,"widgetType":"ennova-business-hours","elType":"widget"}],"isInner":true,"elType":"container"}],"isInner":true,"elType":"container"}],"isInner":false,"elType":"container"},{"id":"37479c83","settings":{"background_background":"classic","background_color":"#121212","border_width":{"unit":"px","top":"1","right":"0","bottom":"0","left":"0","isLinked":false},"border_color":"#343B36","_title":"copyright","border_border":"solid","flex_gap":{"size":10,"unit":"px"}},"elements":[{"id":"347cd514","settings":{"structure":"20","flex_direction":"row","flex_gap":{"size":10,"unit":"px"},"content_width":"full","flex_direction_tablet":"column","min_height":{"unit":"px","size":90,"sizes":[]}},"elements":[{"id":"7954bd10","settings":{"_column_size":50,"width":{"size":60,"unit":"%"},"flex_justify_content":"center","content_width":"full","padding":{"unit":"px","top":"0","right":"10","bottom":"0","left":"10","isLinked":false},"width_tablet":{"unit":"%","size":100,"sizes":[]},"width_mobile":{"unit":"%","size":"","sizes":[]}},"elements":[{"id":"12d63d95","settings":{"copyright":"Copyright \u00a9 [ennova_year] [ennova_site_tile] | All Rights Reserved. Designed by [ennova_site_tile].","align":"left","text_color":"#FFFFFF","caption_typography_typography":"custom","caption_typography_font_family":"Jost","caption_typography_font_size":{"unit":"rem","size":1.100000000000000088817841970012523233890533447265625,"sizes":[]},"caption_typography_font_size_tablet":{"unit":"rem","size":0.90000000000000002220446049250313080847263336181640625,"sizes":[]},"caption_typography_font_size_mobile":{"unit":"rem","size":1,"sizes":[]},"caption_typography_font_weight":"400","site_title_color":"#FFFFFF","site_title_hover_color":"#EB0029","site_title_typography_typography":"custom","site_title_typography_font_family":"Jost","site_title_typography_font_size":{"unit":"rem","size":1.100000000000000088817841970012523233890533447265625,"sizes":[]},"site_title_typography_font_size_tablet":{"unit":"rem","size":0.90000000000000002220446049250313080847263336181640625,"sizes":[]},"site_title_typography_font_size_mobile":{"unit":"rem","size":"","sizes":[]},"site_title_typography_font_weight":"400","ennova_control_get_pro":"1","align_tablet":"center"},"elements":[],"isInner":false,"widgetType":"ennova-copyright","elType":"widget"}],"isInner":true,"elType":"container"},{"id":"ac12cd9","settings":{"_column_size":50,"width":{"size":40,"unit":"%"},"flex_justify_content":"center","content_width":"full","padding":{"unit":"px","top":"0","right":"10","bottom":"0","left":"10","isLinked":false},"width_tablet":{"unit":"%","size":100,"sizes":[]},"width_mobile":{"unit":"%","size":"","sizes":[]}},"elements":[{"id":"1f2a8dc6","settings":{"icon_list":[{"text":"Terms and conditions ","selected_icon":{"value":"","library":""},"_id":"fc52df6","link":{"url":"#","is_external":"","nofollow":"","custom_attributes":""}},{"text":"Privacy policy","selected_icon":{"value":"","library":""},"link":{"url":"#","is_external":"","nofollow":"","custom_attributes":""},"_id":"fbdc84c"}],"space_between":{"unit":"px","size":20,"sizes":[]},"icon_align":"right","icon_color":"#133EC2","icon_color_hover":"#133EC2","icon_size":{"unit":"rem","size":1.100000000000000088817841970012523233890533447265625,"sizes":[]},"icon_size_tablet":{"unit":"rem","size":"","sizes":[]},"icon_size_mobile":{"unit":"rem","size":"","sizes":[]},"text_indent":{"unit":"px","size":2,"sizes":[]},"icon_self_align":"center","icon_self_vertical_align":"center","icon_vertical_offset":{"unit":"px","size":"","sizes":[]},"icon_typography_typography":"custom","icon_typography_font_family":"Jost","icon_typography_font_size":{"unit":"rem","size":1.100000000000000088817841970012523233890533447265625,"sizes":[]},"icon_typography_font_size_tablet":{"unit":"rem","size":0.90000000000000002220446049250313080847263336181640625,"sizes":[]},"icon_typography_font_size_mobile":{"unit":"rem","size":1,"sizes":[]},"icon_typography_font_weight":"400","text_color":"#BDBDBD","text_color_hover":"#EB0029","icon_typography_line_height":{"unit":"em","size":1.600000000000000088817841970012523233890533447265625,"sizes":[]},"icon_typography_line_height_tablet":{"unit":"rem","size":"","sizes":[]},"icon_typography_line_height_mobile":{"unit":"rem","size":"","sizes":[]},"_margin_mobile":{"unit":"px","top":"0","right":"0","bottom":"0","left":"0","isLinked":false},"view":"inline","space_between_mobile":{"unit":"px","size":10,"sizes":[]},"icon_align_mobile":"center","space_between_tablet":{"unit":"px","size":15,"sizes":[]},"icon_align_tablet":"center"},"elements":[],"isInner":false,"widgetType":"icon-list","elType":"widget"}],"isInner":true,"elType":"container"}],"isInner":true,"elType":"container"}],"isInner":false,"elType":"container"},{"id":"12f147d2","settings":{"flex_direction":"column","padding":{"unit":"px","top":"0","right":"0","bottom":"0","left":"0","isLinked":true},"hide_mobile":"hidden-mobile"},"elements":[{"id":"1f7321d1","settings":{"card_title":"Card Title","stt_box_bg_color_color":"#EB0029","stt_box_padding":{"unit":"px","top":"14","right":"17","bottom":"14","left":"17","isLinked":false},"stt_box_box_shadow_box_shadow_type":"yes","stt_box_box_shadow_box_shadow":{"horizontal":0,"vertical":2,"blur":5,"spread":0,"color":"rgba(0, 0, 0, 0.2)"},"stt_box_bg_hover_color_color":"#121212","card_heading_icon_color":"#FFFFFF","card_icon":{"value":"fas fa-arrow-up","library":"fa-solid"},"stt_box_border_radius":{"unit":"px","top":"4","right":"4","bottom":"4","left":"4","isLinked":true}},"elements":[],"isInner":false,"widgetType":"ennova-scroll-to-top","elType":"widget"}],"isInner":false,"elType":"container"}],"page_settings":[],"version":"0.4","title":"Footer","type":"page"}